pmss/__init__.py
pmss/functional.py
pmss/loadfile.py
pmss/parsetab.py
pmss/pathfinder.py
pmss/pmsslex.py
pmss/pmssselectors.py
pmss/pmsstypes.py
pmss/pmssyacc.py
pmss/pretty_usage.py
pmss/priority.py
pmss/rulesets.py
pmss/schema.py
pmss/settings.py
pmss/util.py
pmss-0.0.3.dist-info/METADATA
pmss-0.0.3.dist-info/WHEEL
pmss-0.0.3.dist-info/top_level.txt
pmss-0.0.3.dist-info/RECORD
