Metadata-Version: 2.4
Name: pmss
Version: 0.0.3
Summary: Cascading Python settings
Author: Bradley Erickson
Author-email: Piotr Mitros <piotr@mitros.org>
Project-URL: Homepage, https://github.com/ETS-Next-Gen/pmss
Classifier: Programming Language :: Python :: 3
Classifier: License :: OSI Approved :: MIT License
Classifier: Operating System :: OS Independent
Requires-Python: >=3.8
Requires-Dist: ply
Requires-Dist: pyyaml
